log2frame/__init__.py
log2frame/debug.py
log2frame/dlis.py
log2frame/las.py
log2frame/lis.py
log2frame/log.py
log2frame/pack.py
log2frame/rft.py
log2frame/dictionaries/__init__.py
log2frame/dictionaries/units.py
log2frame-0.1.19.dist-info/LICENSE
log2frame-0.1.19.dist-info/METADATA
log2frame-0.1.19.dist-info/WHEEL
log2frame-0.1.19.dist-info/top_level.txt
log2frame-0.1.19.dist-info/RECORD
