Metadata-Version: 2.1
Name: log2frame
Version: 0.1.19
Summary: A function to facilitate loading well log data, in las or dlis format, as dataframe.
Author-email: Martin Carlos Araya <martinaraya@gmail.com>
License: MIT License
Project-URL: Homepage, https://github.com/ayaranitram/log2frame
Project-URL: Bug Tracker, https://github.com/ayaranitram/log2frame/issues
Classifier: Programming Language :: Python :: 3.7
Classifier: Programming Language :: Python :: 3.8
Classifier: Programming Language :: Python :: 3.9
Classifier: Programming Language :: Python :: 3.10
Classifier: Programming Language :: Python :: 3.11
Classifier: License :: OSI Approved :: MIT License
Classifier: Operating System :: OS Independent
Requires-Python: >=3.7
License-File: LICENSE
Requires-Dist: lasio
Requires-Dist: dlisio
Requires-Dist: pandas
Requires-Dist: unyts (>=0.5.17)
